{
  "https://opensource-demo.orangehrmlive.com/web/index.php/api/v2/pim/employees/7/custom-fields?screen=personal" : {
    "transaction" : "https://opensource-demo.orangehrmlive.com/web/index.php/api/v2/pim/employees/7/custom-fields?screen=personal",
    "sampleCount" : 1,
    "errorCount" : 0,
    "errorPct" : 0.0,
    "meanResTime" : 334.0,
    "medianResTime" : 334.0,
    "minResTime" : 334.0,
    "maxResTime" : 334.0,
    "pct1ResTime" : 334.0,
    "pct2ResTime" : 334.0,
    "pct3ResTime" : 334.0,
    "throughput" : 2.9940119760479043,
    "receivedKBytesPerSec" : 3.5612369011976046,
    "sentKBytesPerSec" : 1.9209627619760479
  },
  "https://opensource-demo.orangehrmlive.com/web/index.php/auth/validate-0" : {
    "transaction" : "https://opensource-demo.orangehrmlive.com/web/index.php/auth/validate-0",
    "sampleCount" : 3,
    "errorCount" : 0,
    "errorPct" : 0.0,
    "meanResTime" : 949.0,
    "medianResTime" : 943.0,
    "minResTime" : 937.0,
    "maxResTime" : 967.0,
    "pct1ResTime" : 967.0,
    "pct2ResTime" : 967.0,
    "pct3ResTime" : 967.0,
    "throughput" : 0.075340917652377,
    "receivedKBytesPerSec" : 0.13074297916823627,
    "sentKBytesPerSec" : 0.06967563380546975
  },
  "https://opensource-demo.orangehrmlive.com/web/index.php/auth/validate-1" : {
    "transaction" : "https://opensource-demo.orangehrmlive.com/web/index.php/auth/validate-1",
    "sampleCount" : 3,
    "errorCount" : 0,
    "errorPct" : 0.0,
    "meanResTime" : 327.6666666666667,
    "medianResTime" : 312.0,
    "minResTime" : 298.0,
    "maxResTime" : 373.0,
    "pct1ResTime" : 373.0,
    "pct2ResTime" : 373.0,
    "pct3ResTime" : 373.0,
    "throughput" : 0.07656772415201246,
    "receivedKBytesPerSec" : 0.12636665411806744,
    "sentKBytesPerSec" : 0.057425793114009346
  },
  "https://opensource-demo.orangehrmlive.com/web/index.php/auth/validate-2" : {
    "transaction" : "https://opensource-demo.orangehrmlive.com/web/index.php/auth/validate-2",
    "sampleCount" : 3,
    "errorCount" : 0,
    "errorPct" : 0.0,
    "meanResTime" : 362.3333333333333,
    "medianResTime" : 365.0,
    "minResTime" : 355.0,
    "maxResTime" : 367.0,
    "pct1ResTime" : 367.0,
    "pct2ResTime" : 367.0,
    "pct3ResTime" : 367.0,
    "throughput" : 0.07660878447395301,
    "receivedKBytesPerSec" : 0.5900522296348315,
    "sentKBytesPerSec" : 0.057681028153728296
  },
  "https://opensource-demo.orangehrmlive.com/web/index.php/api/v2/pim/employees/7/screen/personal/attachments?limit=50&offset=0" : {
    "transaction" : "https://opensource-demo.orangehrmlive.com/web/index.php/api/v2/pim/employees/7/screen/personal/attachments?limit=50&offset=0",
    "sampleCount" : 1,
    "errorCount" : 0,
    "errorPct" : 0.0,
    "meanResTime" : 327.0,
    "medianResTime" : 327.0,
    "minResTime" : 327.0,
    "maxResTime" : 327.0,
    "pct1ResTime" : 327.0,
    "pct2ResTime" : 327.0,
    "pct3ResTime" : 327.0,
    "throughput" : 3.058103975535168,
    "receivedKBytesPerSec" : 3.3268826452599387,
    "sentKBytesPerSec" : 2.0098671636085625
  },
  "https://opensource-demo.orangehrmlive.com/web/index.php/auth/validate" : {
    "transaction" : "https://opensource-demo.orangehrmlive.com/web/index.php/auth/validate",
    "sampleCount" : 3,
    "errorCount" : 0,
    "errorPct" : 0.0,
    "meanResTime" : 1825.6666666666667,
    "medianResTime" : 1807.0,
    "minResTime" : 1800.0,
    "maxResTime" : 1870.0,
    "pct1ResTime" : 1870.0,
    "pct2ResTime" : 1870.0,
    "pct3ResTime" : 1870.0,
    "throughput" : 0.07379710715339959,
    "receivedKBytesPerSec" : 1.1760693277698513,
    "sentKBytesPerSec" : 0.48984271222818065
  },
  "https://opensource-demo.orangehrmlive.com/web/index.php/auth/validate-3" : {
    "transaction" : "https://opensource-demo.orangehrmlive.com/web/index.php/auth/validate-3",
    "sampleCount" : 3,
    "errorCount" : 0,
    "errorPct" : 0.0,
    "meanResTime" : 155.0,
    "medianResTime" : 156.0,
    "minResTime" : 148.0,
    "maxResTime" : 161.0,
    "pct1ResTime" : 161.0,
    "pct2ResTime" : 161.0,
    "pct3ResTime" : 161.0,
    "throughput" : 0.07706931100035964,
    "receivedKBytesPerSec" : 0.07458563203257462,
    "sentKBytesPerSec" : 0.06450039016338693
  },
  "https://opensource-demo.orangehrmlive.com/web/index.php/pim/viewMyDetails-0" : {
    "transaction" : "https://opensource-demo.orangehrmlive.com/web/index.php/pim/viewMyDetails-0",
    "sampleCount" : 2,
    "errorCount" : 0,
    "errorPct" : 0.0,
    "meanResTime" : 780.0,
    "medianResTime" : 780.0,
    "minResTime" : 568.0,
    "maxResTime" : 992.0,
    "pct1ResTime" : 992.0,
    "pct2ResTime" : 992.0,
    "pct3ResTime" : 992.0,
    "throughput" : 0.07152564194263644,
    "receivedKBytesPerSec" : 1.508464612688649,
    "sentKBytesPerSec" : 0.05022161773120664
  },
  "https://opensource-demo.orangehrmlive.com/" : {
    "transaction" : "https://opensource-demo.orangehrmlive.com/",
    "sampleCount" : 3,
    "errorCount" : 0,
    "errorPct" : 0.0,
    "meanResTime" : 3277.3333333333335,
    "medianResTime" : 2923.0,
    "minResTime" : 2698.0,
    "maxResTime" : 4211.0,
    "pct1ResTime" : 4211.0,
    "pct2ResTime" : 4211.0,
    "pct3ResTime" : 4211.0,
    "throughput" : 0.18298261665141813,
    "receivedKBytesPerSec" : 650.2113949565417,
    "sentKBytesPerSec" : 0.8707756747483989
  },
  "https://opensource-demo.orangehrmlive.com/web/index.php/auth/validate-4" : {
    "transaction" : "https://opensource-demo.orangehrmlive.com/web/index.php/auth/validate-4",
    "sampleCount" : 3,
    "errorCount" : 0,
    "errorPct" : 0.0,
    "meanResTime" : 155.66666666666666,
    "medianResTime" : 155.0,
    "minResTime" : 152.0,
    "maxResTime" : 160.0,
    "pct1ResTime" : 160.0,
    "pct2ResTime" : 160.0,
    "pct3ResTime" : 160.0,
    "throughput" : 0.07706139224248651,
    "receivedKBytesPerSec" : 0.07472847900077062,
    "sentKBytesPerSec" : 0.06539682603390701
  },
  "https://opensource-demo.orangehrmlive.com/web/index.php/pim/viewMyDetails-1" : {
    "transaction" : "https://opensource-demo.orangehrmlive.com/web/index.php/pim/viewMyDetails-1",
    "sampleCount" : 2,
    "errorCount" : 0,
    "errorPct" : 0.0,
    "meanResTime" : 338.5,
    "medianResTime" : 338.5,
    "minResTime" : 157.0,
    "maxResTime" : 520.0,
    "pct1ResTime" : 520.0,
    "pct2ResTime" : 520.0,
    "pct3ResTime" : 520.0,
    "throughput" : 0.07168201856564281,
    "receivedKBytesPerSec" : 0.06937195351421097,
    "sentKBytesPerSec" : 0.05656159277445253
  },
  "https://opensource-demo.orangehrmlive.com/web/index.php/auth/validate-5" : {
    "transaction" : "https://opensource-demo.orangehrmlive.com/web/index.php/auth/validate-5",
    "sampleCount" : 3,
    "errorCount" : 0,
    "errorPct" : 0.0,
    "meanResTime" : 151.66666666666666,
    "medianResTime" : 152.0,
    "minResTime" : 147.0,
    "maxResTime" : 156.0,
    "pct1ResTime" : 156.0,
    "pct2ResTime" : 156.0,
    "pct3ResTime" : 156.0,
    "throughput" : 0.07707129094412332,
    "receivedKBytesPerSec" : 0.07473807803468209,
    "sentKBytesPerSec" : 0.06465257707129095
  },
  "https://opensource-demo.orangehrmlive.com/web/index.php/auth/validate-6" : {
    "transaction" : "https://opensource-demo.orangehrmlive.com/web/index.php/auth/validate-6",
    "sampleCount" : 3,
    "errorCount" : 0,
    "errorPct" : 0.0,
    "meanResTime" : 151.33333333333334,
    "medianResTime" : 151.0,
    "minResTime" : 149.0,
    "maxResTime" : 154.0,
    "pct1ResTime" : 154.0,
    "pct2ResTime" : 154.0,
    "pct3ResTime" : 154.0,
    "throughput" : 0.07706337177939326,
    "receivedKBytesPerSec" : 0.07480565580929384,
    "sentKBytesPerSec" : 0.06532324873487631
  },
  "https://opensource-demo.orangehrmlive.com/web/index.php/auth/validate-7" : {
    "transaction" : "https://opensource-demo.orangehrmlive.com/web/index.php/auth/validate-7",
    "sampleCount" : 3,
    "errorCount" : 0,
    "errorPct" : 0.0,
    "meanResTime" : 155.33333333333334,
    "medianResTime" : 156.0,
    "minResTime" : 152.0,
    "maxResTime" : 158.0,
    "pct1ResTime" : 158.0,
    "pct2ResTime" : 158.0,
    "pct3ResTime" : 158.0,
    "throughput" : 0.07705347511172754,
    "receivedKBytesPerSec" : 0.07479604908306366,
    "sentKBytesPerSec" : 0.06456238441978733
  },
  "01_Homepage" : {
    "transaction" : "01_Homepage",
    "sampleCount" : 3,
    "errorCount" : 0,
    "errorPct" : 0.0,
    "meanResTime" : 3678.6666666666665,
    "medianResTime" : 3234.0,
    "minResTime" : 3003.0,
    "maxResTime" : 4799.0,
    "pct1ResTime" : 4799.0,
    "pct2ResTime" : 4799.0,
    "pct3ResTime" : 4799.0,
    "throughput" : 0.17728400898238977,
    "receivedKBytesPerSec" : 646.4582325338316,
    "sentKBytesPerSec" : 0.9508240013000827
  },
  "https://opensource-demo.orangehrmlive.com/web/index.php/api/v2/pim/employees?limit=50&offset=0&model=detailed&includeEmployees=onlyCurrent&sortField=employee.firstName&sortOrder=ASC" : {
    "transaction" : "https://opensource-demo.orangehrmlive.com/web/index.php/api/v2/pim/employees?limit=50&offset=0&model=detailed&includeEmployees=onlyCurrent&sortField=employee.firstName&sortOrder=ASC",
    "sampleCount" : 3,
    "errorCount" : 0,
    "errorPct" : 0.0,
    "meanResTime" : 441.3333333333333,
    "medianResTime" : 448.0,
    "minResTime" : 401.0,
    "maxResTime" : 475.0,
    "pct1ResTime" : 475.0,
    "pct2ResTime" : 475.0,
    "pct3ResTime" : 475.0,
    "throughput" : 0.07641559897093661,
    "receivedKBytesPerSec" : 0.9386034492090986,
    "sentKBytesPerSec" : 0.05447596411014035
  },
  "https://opensource-demo.orangehrmlive.com/web/index.php/pim/viewMyDetails" : {
    "transaction" : "https://opensource-demo.orangehrmlive.com/web/index.php/pim/viewMyDetails",
    "sampleCount" : 2,
    "errorCount" : 0,
    "errorPct" : 0.0,
    "meanResTime" : 1157.0,
    "medianResTime" : 1157.0,
    "minResTime" : 765.0,
    "maxResTime" : 1549.0,
    "pct1ResTime" : 1549.0,
    "pct2ResTime" : 1549.0,
    "pct3ResTime" : 1549.0,
    "throughput" : 0.07012868613906517,
    "receivedKBytesPerSec" : 1.819031281777061,
    "sentKBytesPerSec" : 0.32770094060100285
  },
  "https://opensource-demo.orangehrmlive.com/web/index.php/api/v2/pim/employees/7" : {
    "transaction" : "https://opensource-demo.orangehrmlive.com/web/index.php/api/v2/pim/employees/7",
    "sampleCount" : 1,
    "errorCount" : 0,
    "errorPct" : 0.0,
    "meanResTime" : 436.0,
    "medianResTime" : 436.0,
    "minResTime" : 436.0,
    "maxResTime" : 436.0,
    "pct1ResTime" : 436.0,
    "pct2ResTime" : 436.0,
    "pct3ResTime" : 436.0,
    "throughput" : 2.293577981651376,
    "receivedKBytesPerSec" : 2.6497097190366974,
    "sentKBytesPerSec" : 1.2654995699541285
  },
  "https://opensource-demo.orangehrmlive.com/web/index.php/core/i18n/messages" : {
    "transaction" : "https://opensource-demo.orangehrmlive.com/web/index.php/core/i18n/messages",
    "sampleCount" : 7,
    "errorCount" : 0,
    "errorPct" : 0.0,
    "meanResTime" : 342.14285714285717,
    "medianResTime" : 305.0,
    "minResTime" : 277.0,
    "maxResTime" : 588.0,
    "pct1ResTime" : 588.0,
    "pct2ResTime" : 588.0,
    "pct3ResTime" : 588.0,
    "throughput" : 0.11949266827128249,
    "receivedKBytesPerSec" : 4.835352172632764,
    "sentKBytesPerSec" : 0.07643329855243167
  },
  "https://opensource-demo.orangehrmlive.com/-6" : {
    "transaction" : "https://opensource-demo.orangehrmlive.com/-6",
    "sampleCount" : 3,
    "errorCount" : 0,
    "errorPct" : 0.0,
    "meanResTime" : 1881.0,
    "medianResTime" : 1772.0,
    "minResTime" : 1768.0,
    "maxResTime" : 2103.0,
    "pct1ResTime" : 2103.0,
    "pct2ResTime" : 2103.0,
    "pct3ResTime" : 2103.0,
    "throughput" : 0.21100014066676046,
    "receivedKBytesPerSec" : 300.7633919151779,
    "sentKBytesPerSec" : 0.14691709013222676
  },
  "https://opensource-demo.orangehrmlive.com/-5" : {
    "transaction" : "https://opensource-demo.orangehrmlive.com/-5",
    "sampleCount" : 3,
    "errorCount" : 0,
    "errorPct" : 0.0,
    "meanResTime" : 1918.0,
    "medianResTime" : 1849.0,
    "minResTime" : 1795.0,
    "maxResTime" : 2110.0,
    "pct1ResTime" : 2110.0,
    "pct2ResTime" : 2110.0,
    "pct3ResTime" : 2110.0,
    "throughput" : 0.20976087260523005,
    "receivedKBytesPerSec" : 237.7166299949308,
    "sentKBytesPerSec" : 0.148102647357013
  },
  "https://opensource-demo.orangehrmlive.com/-4" : {
    "transaction" : "https://opensource-demo.orangehrmlive.com/-4",
    "sampleCount" : 3,
    "errorCount" : 0,
    "errorPct" : 0.0,
    "meanResTime" : 1526.0,
    "medianResTime" : 1526.0,
    "minResTime" : 1481.0,
    "maxResTime" : 1571.0,
    "pct1ResTime" : 1571.0,
    "pct2ResTime" : 1571.0,
    "pct3ResTime" : 1571.0,
    "throughput" : 0.21451555237754738,
    "receivedKBytesPerSec" : 102.4695125357526,
    "sentKBytesPerSec" : 0.1497838085448695
  },
  "https://opensource-demo.orangehrmlive.com/-3" : {
    "transaction" : "https://opensource-demo.orangehrmlive.com/-3",
    "sampleCount" : 3,
    "errorCount" : 0,
    "errorPct" : 0.0,
    "meanResTime" : 1429.6666666666667,
    "medianResTime" : 1362.0,
    "minResTime" : 1271.0,
    "maxResTime" : 1656.0,
    "pct1ResTime" : 1656.0,
    "pct2ResTime" : 1656.0,
    "pct3ResTime" : 1656.0,
    "throughput" : 0.21229920033967872,
    "receivedKBytesPerSec" : 108.28503157950605,
    "sentKBytesPerSec" : 0.15030949242799518
  },
  "https://opensource-demo.orangehrmlive.com/-2" : {
    "transaction" : "https://opensource-demo.orangehrmlive.com/-2",
    "sampleCount" : 3,
    "errorCount" : 0,
    "errorPct" : 0.0,
    "meanResTime" : 290.6666666666667,
    "medianResTime" : 167.0,
    "minResTime" : 152.0,
    "maxResTime" : 553.0,
    "pct1ResTime" : 553.0,
    "pct2ResTime" : 553.0,
    "pct3ResTime" : 553.0,
    "throughput" : 0.2374544878898211,
    "receivedKBytesPerSec" : 0.38818243430425836,
    "sentKBytesPerSec" : 0.16580074105588094
  },
  "https://opensource-demo.orangehrmlive.com/-1" : {
    "transaction" : "https://opensource-demo.orangehrmlive.com/-1",
    "sampleCount" : 3,
    "errorCount" : 0,
    "errorPct" : 0.0,
    "meanResTime" : 313.6666666666667,
    "medianResTime" : 313.0,
    "minResTime" : 304.0,
    "maxResTime" : 324.0,
    "pct1ResTime" : 324.0,
    "pct2ResTime" : 324.0,
    "pct3ResTime" : 324.0,
    "throughput" : 0.2237303303751212,
    "receivedKBytesPerSec" : 0.9646185630919532,
    "sentKBytesPerSec" : 0.14267178294429114
  },
  "https://opensource-demo.orangehrmlive.com/-0" : {
    "transaction" : "https://opensource-demo.orangehrmlive.com/-0",
    "sampleCount" : 3,
    "errorCount" : 0,
    "errorPct" : 0.0,
    "meanResTime" : 708.0,
    "medianResTime" : 524.0,
    "minResTime" : 484.0,
    "maxResTime" : 1116.0,
    "pct1ResTime" : 1116.0,
    "pct2ResTime" : 1116.0,
    "pct3ResTime" : 1116.0,
    "throughput" : 0.21095562899936712,
    "receivedKBytesPerSec" : 0.21713596969270796,
    "sentKBytesPerSec" : 0.1295811432037128
  },
  "https://opensource-demo.orangehrmlive.com/web/index.php/api/v2/pim/employees/7/personal-details" : {
    "transaction" : "https://opensource-demo.orangehrmlive.com/web/index.php/api/v2/pim/employees/7/personal-details",
    "sampleCount" : 1,
    "errorCount" : 0,
    "errorPct" : 0.0,
    "meanResTime" : 391.0,
    "medianResTime" : 391.0,
    "minResTime" : 391.0,
    "maxResTime" : 391.0,
    "pct1ResTime" : 391.0,
    "pct2ResTime" : 391.0,
    "pct3ResTime" : 391.0,
    "throughput" : 2.557544757033248,
    "receivedKBytesPerSec" : 3.579064098465473,
    "sentKBytesPerSec" : 1.6084558823529411
  },
  "02_Login" : {
    "transaction" : "02_Login",
    "sampleCount" : 3,
    "errorCount" : 0,
    "errorPct" : 0.0,
    "meanResTime" : 3518.0,
    "medianResTime" : 3526.0,
    "minResTime" : 3491.0,
    "maxResTime" : 3537.0,
    "pct1ResTime" : 3537.0,
    "pct2ResTime" : 3537.0,
    "pct3ResTime" : 3537.0,
    "throughput" : 0.2306805074971165,
    "receivedKBytesPerSec" : 8.602685866013072,
    "sentKBytesPerSec" : 2.2752667243367934
  },
  "03_Go To My Info" : {
    "transaction" : "03_Go To My Info",
    "sampleCount" : 3,
    "errorCount" : 0,
    "errorPct" : 0.0,
    "meanResTime" : 12551.0,
    "medianResTime" : 5365.0,
    "minResTime" : 0.0,
    "maxResTime" : 32288.0,
    "pct1ResTime" : 32288.0,
    "pct2ResTime" : 32288.0,
    "pct3ResTime" : 32288.0,
    "throughput" : 0.057515337423312884,
    "receivedKBytesPerSec" : 1.3492701243769172,
    "sentKBytesPerSec" : 0.29420443107745403
  },
  "https://opensource-demo.orangehrmlive.com/web/index.php/api/v2/admin/employment-statuses" : {
    "transaction" : "https://opensource-demo.orangehrmlive.com/web/index.php/api/v2/admin/employment-statuses",
    "sampleCount" : 3,
    "errorCount" : 0,
    "errorPct" : 0.0,
    "meanResTime" : 316.6666666666667,
    "medianResTime" : 317.0,
    "minResTime" : 310.0,
    "maxResTime" : 323.0,
    "pct1ResTime" : 323.0,
    "pct2ResTime" : 323.0,
    "pct3ResTime" : 323.0,
    "throughput" : 0.0765774964263835,
    "receivedKBytesPerSec" : 0.0969931766259955,
    "sentKBytesPerSec" : 0.047636587132428014
  },
  "https://opensource-demo.orangehrmlive.com/web/index.php/api/v2/pim/employees" : {
    "transaction" : "https://opensource-demo.orangehrmlive.com/web/index.php/api/v2/pim/employees",
    "sampleCount" : 1,
    "errorCount" : 0,
    "errorPct" : 0.0,
    "meanResTime" : 423.0,
    "medianResTime" : 423.0,
    "minResTime" : 423.0,
    "maxResTime" : 423.0,
    "pct1ResTime" : 423.0,
    "pct2ResTime" : 423.0,
    "pct3ResTime" : 423.0,
    "throughput" : 2.3640661938534278,
    "receivedKBytesPerSec" : 10.94534943853428,
    "sentKBytesPerSec" : 1.2997746749408985
  },
  "04_Click Personal Details" : {
    "transaction" : "04_Click Personal Details",
    "sampleCount" : 1,
    "errorCount" : 0,
    "errorPct" : 0.0,
    "meanResTime" : 0.0,
    "medianResTime" : 0.0,
    "minResTime" : 0.0,
    "maxResTime" : 0.0,
    "pct1ResTime" : 0.0,
    "pct2ResTime" : 0.0,
    "pct3ResTime" : 0.0,
    "throughput" : "Infinity",
    "receivedKBytesPerSec" : "NaN",
    "sentKBytesPerSec" : "NaN"
  },
  "https://opensource-demo.orangehrmlive.com/web/index.php/pim/viewMyDetails-4" : {
    "transaction" : "https://opensource-demo.orangehrmlive.com/web/index.php/pim/viewMyDetails-4",
    "sampleCount" : 2,
    "errorCount" : 0,
    "errorPct" : 0.0,
    "meanResTime" : 342.5,
    "medianResTime" : 342.5,
    "minResTime" : 160.0,
    "maxResTime" : 525.0,
    "pct1ResTime" : 525.0,
    "pct2ResTime" : 525.0,
    "pct3ResTime" : 525.0,
    "throughput" : 0.07166147121000394,
    "receivedKBytesPerSec" : 0.06956201404564837,
    "sentKBytesPerSec" : 0.057315180586907453
  },
  "https://opensource-demo.orangehrmlive.com/web/index.php/api/v2/leave/holidays?fromDate=2022-01-01&toDate=2022-12-31" : {
    "transaction" : "https://opensource-demo.orangehrmlive.com/web/index.php/api/v2/leave/holidays?fromDate=2022-01-01&toDate=2022-12-31",
    "sampleCount" : 2,
    "errorCount" : 0,
    "errorPct" : 0.0,
    "meanResTime" : 632.5,
    "medianResTime" : 632.5,
    "minResTime" : 481.0,
    "maxResTime" : 784.0,
    "pct1ResTime" : 784.0,
    "pct2ResTime" : 784.0,
    "pct3ResTime" : 784.0,
    "throughput" : 1.0804970286331712,
    "receivedKBytesPerSec" : 3.1549669097784983,
    "sentKBytesPerSec" : 0.635214073473798
  },
  "https://opensource-demo.orangehrmlive.com/web/index.php/api/v2/leave/workweek?model=indexed" : {
    "transaction" : "https://opensource-demo.orangehrmlive.com/web/index.php/api/v2/leave/workweek?model=indexed",
    "sampleCount" : 2,
    "errorCount" : 0,
    "errorPct" : 0.0,
    "meanResTime" : 539.0,
    "medianResTime" : 539.0,
    "minResTime" : 502.0,
    "maxResTime" : 576.0,
    "pct1ResTime" : 576.0,
    "pct2ResTime" : 576.0,
    "pct3ResTime" : 576.0,
    "throughput" : 1.070090957731407,
    "receivedKBytesPerSec" : 1.16205189941145,
    "sentKBytesPerSec" : 0.6040161851257357
  },
  "https://opensource-demo.orangehrmlive.com/web/index.php/pim/viewMyDetails-5" : {
    "transaction" : "https://opensource-demo.orangehrmlive.com/web/index.php/pim/viewMyDetails-5",
    "sampleCount" : 2,
    "errorCount" : 0,
    "errorPct" : 0.0,
    "meanResTime" : 343.5,
    "medianResTime" : 343.5,
    "minResTime" : 157.0,
    "maxResTime" : 530.0,
    "pct1ResTime" : 530.0,
    "pct2ResTime" : 530.0,
    "pct3ResTime" : 530.0,
    "throughput" : 0.07164863509350147,
    "receivedKBytesPerSec" : 0.06954955398724653,
    "sentKBytesPerSec" : 0.056605220498674495
  },
  "https://opensource-demo.orangehrmlive.com/web/index.php/api/v2/admin/subunits" : {
    "transaction" : "https://opensource-demo.orangehrmlive.com/web/index.php/api/v2/admin/subunits",
    "sampleCount" : 3,
    "errorCount" : 0,
    "errorPct" : 0.0,
    "meanResTime" : 312.6666666666667,
    "medianResTime" : 313.0,
    "minResTime" : 304.0,
    "maxResTime" : 321.0,
    "pct1ResTime" : 321.0,
    "pct2ResTime" : 321.0,
    "pct3ResTime" : 321.0,
    "throughput" : 0.07655600071452268,
    "receivedKBytesPerSec" : 0.16806434531860057,
    "sentKBytesPerSec" : 0.04680083637430781
  },
  "https://opensource-demo.orangehrmlive.com/web/index.php/pim/viewMyDetails-2" : {
    "transaction" : "https://opensource-demo.orangehrmlive.com/web/index.php/pim/viewMyDetails-2",
    "sampleCount" : 2,
    "errorCount" : 0,
    "errorPct" : 0.0,
    "meanResTime" : 167.5,
    "medianResTime" : 167.5,
    "minResTime" : 162.0,
    "maxResTime" : 173.0,
    "pct1ResTime" : 173.0,
    "pct2ResTime" : 173.0,
    "pct3ResTime" : 173.0,
    "throughput" : 0.07257947452460443,
    "receivedKBytesPerSec" : 0.07038224433880098,
    "sentKBytesPerSec" : 0.0581202823341559
  },
  "Total" : {
    "transaction" : "Total",
    "sampleCount" : 96,
    "errorCount" : 0,
    "errorPct" : 0.0,
    "meanResTime" : 1008.1562499999998,
    "medianResTime" : 366.0,
    "minResTime" : 0.0,
    "maxResTime" : 32288.0,
    "pct1ResTime" : 1802.1,
    "pct2ResTime" : 2198.199999999995,
    "pct3ResTime" : 32288.0,
    "throughput" : 1.2006903969782625,
    "receivedKBytesPerSec" : 274.0008366138655,
    "sentKBytesPerSec" : 1.3662030472209021
  },
  "https://opensource-demo.orangehrmlive.com/web/index.php/pim/viewMyDetails-3" : {
    "transaction" : "https://opensource-demo.orangehrmlive.com/web/index.php/pim/viewMyDetails-3",
    "sampleCount" : 2,
    "errorCount" : 0,
    "errorPct" : 0.0,
    "meanResTime" : 311.0,
    "medianResTime" : 311.0,
    "minResTime" : 151.0,
    "maxResTime" : 471.0,
    "pct1ResTime" : 471.0,
    "pct2ResTime" : 471.0,
    "pct3ResTime" : 471.0,
    "throughput" : 0.07179523997558962,
    "receivedKBytesPerSec" : 0.06962175126539111,
    "sentKBytesPerSec" : 0.05679115662131601
  },
  "https://opensource-demo.orangehrmlive.com/web/index.php/api/v2/admin/job-titles" : {
    "transaction" : "https://opensource-demo.orangehrmlive.com/web/index.php/api/v2/admin/job-titles",
    "sampleCount" : 3,
    "errorCount" : 0,
    "errorPct" : 0.0,
    "meanResTime" : 340.0,
    "medianResTime" : 332.0,
    "minResTime" : 316.0,
    "maxResTime" : 372.0,
    "pct1ResTime" : 372.0,
    "pct2ResTime" : 372.0,
    "pct3ResTime" : 372.0,
    "throughput" : 0.07656186198448346,
    "receivedKBytesPerSec" : 0.3509583790577787,
    "sentKBytesPerSec" : 0.0469539544201715
  }
}